Metadata-Version: 2.4
Name: llama-index-vector-stores-pgvecto-rs
Version: 0.4.1
Summary: llama-index vector_stores pgvecto rs integration
Author-email: Your Name <you@example.com>
License-Expression: MIT
License-File: LICENSE
Requires-Python: <4.0,>=3.9
Requires-Dist: llama-index-core<0.15,>=0.13.0
Requires-Dist: pgvecto-rs[sdk]<0.2,>=0.1.4
